[
  {
    "name": "ZenMine Pro",
    "url": "https://zenmine.pro/"
  },
  {
    "name": "Luckpool",
    "url": "http://www.luckpool.org/"
  },
  {
    "name": "ZHash.pro",
    "url": "https://zhash.pro/"
  },
  {
    "name": "Miningspeed",
    "url": "http://zen.miningspeed.com/"
  },
  {
    "name": "Mining Pool Hub",
    "url": "https://miningpoolhub.com/"
  },
  {
    "name": "TreeFrog Mines",
    "url": "https://treefrogmines.com/"
  },
  {
    "name": "MineZ Zone",
    "url": "https://minez.zone/"
  },
  {
    "name": "HebUsio Pool",
    "url": "https://zenpool-eu.hebusio.com"
  },
  {
    "name": "SuprNova",
    "url": "https://zen.suprnova.cc/"
  },
  {
    "name": "Owl Miners' Club",
    "url": "http://zen.owlminingclub.com/"
  },
  {
    "name": "Miner Maniac",
    "url": "http://www.minermaniac.com/"
  },
  {
    "name": "Nibiru Pool",
    "url": "http://zen.nibirupool.com/"
  },
  {
    "name": "Catspool",
    "url": "http://zen.catspool.org/"
  },
  {
    "name": "2miners",
    "url": "https://2miners.com/"
  },
  {
    "name": "MyZen.Cash EU POOL",
    "url": "https://myzen.cash/"
  },
  {
    "name": "MinerBay",
    "url": "https://minerbay.org/"
  },
  {
    "name": "Ambit",
    "url": "https://www.ambitmining.io/"
  }
]
